mcp_server_lib/__init__.py
mcp_server_lib/akshare_provider.py
mcp_server_lib/app.py
mcp_server_lib/cli.py
mcp_server_lib/yahoo_finance_provider.py
hstock_mcp-0.2.0.dist-info/METADATA
hstock_mcp-0.2.0.dist-info/WHEEL
hstock_mcp-0.2.0.dist-info/entry_points.txt
hstock_mcp-0.2.0.dist-info/top_level.txt
hstock_mcp-0.2.0.dist-info/RECORD
