Metadata-Version: 2.4
Name: hstock-mcp
Version: 0.2.0
Summary: A Flask server to provide A-share market data via MCP.
Author-email: Manus AI <contact@manus.ai>
License: MIT
Project-URL: Homepage, https://github.com/manus-team/hstock-mcp-example
Classifier: Programming Language :: Python :: 3
Classifier: License :: OSI Approved :: MIT License
Classifier: Operating System :: OS Independent
Classifier: Framework :: Flask
Classifier: Topic :: Office/Business :: Financial :: Investment
Requires-Dist: Flask
Requires-Dist: akshare
